video_ocr.py
video_ocr-0.0.2.dist-info/LICENSE
video_ocr-0.0.2.dist-info/METADATA
video_ocr-0.0.2.dist-info/WHEEL
video_ocr-0.0.2.dist-info/entry_points.txt
video_ocr-0.0.2.dist-info/top_level.txt
video_ocr-0.0.2.dist-info/RECORD
