Metadata-Version: 2.1
Name: video-ocr
Version: 0.0.2
Summary: Package to run OCR on videos
Author: Veneet Reddy
License: UNKNOWN
Project-URL: Documentation, https://github.com/PinkFloyded/video-ocr
Project-URL: Source, https://github.com/PinkFloyded/video-ocr
Project-URL: Tracker, https://github.com/PinkFloyded/video-ocr/issues
Platform: UNKNOWN
Classifier: Programming Language :: Python :: 3
Classifier: License :: OSI Approved :: MIT License
Classifier: Operating System :: OS Independent
Classifier: Development Status :: 2 - Pre-Alpha
Classifier: Intended Audience :: End Users/Desktop
Classifier: Intended Audience :: Developers
Classifier: Topic :: Scientific/Engineering :: Image Processing
Classifier: Topic :: Scientific/Engineering :: Image Recognition
Requires-Python: >=3.6
License-File: LICENSE
Requires-Dist: tesserocr (~=2.5.2)
Requires-Dist: scipy (~=1.8.0)
Requires-Dist: opencv-python (~=4.5.5.62)
Requires-Dist: numpy (~=1.22.2)
Requires-Dist: tqdm (~=4.62.3)
Requires-Dist: click (~=8.0.1)
Requires-Dist: Pillow (~=9.0.1)
Provides-Extra: dev
Requires-Dist: flake8 (~=4.0.1) ; extra == 'dev'
Requires-Dist: black (~=22.1.0) ; extra == 'dev'
